mccoy/__init__.py
mccoy/config/config.yaml
mccoy/main.py
mccoy/profiles/local/config.yaml
mccoy/profiles/slurm/config.yaml
mccoy/profiles/slurm/slurm-cancel
mccoy/resources_registry.txt
mccoy/tests.py
mccoy/workflow/Snakefile
mccoy/workflow/envs/arviz.yml
mccoy/workflow/envs/beast.post-deploy.sh
mccoy/workflow/envs/beast.yml
mccoy/workflow/envs/combine.yml
mccoy/workflow/envs/dendropy.yml
mccoy/workflow/envs/dynamicbeast.yml
mccoy/workflow/envs/graphviz.yml
mccoy/workflow/envs/iqtree.yml
mccoy/workflow/envs/jinja.yml
mccoy/workflow/envs/mafft.yml
mccoy/workflow/envs/phytest.yml
mccoy/workflow/envs/plot_traces.yml
mccoy/workflow/envs/steenwyk.yml
mccoy/workflow/envs/toytree.yml
mccoy/workflow/report/alignment.html
mccoy/workflow/report/assets/css/_variables.scss
mccoy/workflow/report/assets/css/bootstrap.min.css
mccoy/workflow/report/assets/css/cosmo/_variables.scss
mccoy/workflow/report/assets/css/cosmo/bootstrap.cosmo.min.css
mccoy/workflow/report/assets/css/custom.sass
mccoy/workflow/report/assets/img/mccoy-logo.svg
mccoy/workflow/report/beast.html
mccoy/workflow/report/bibliography.bib
mccoy/workflow/report/bibliography.html
mccoy/workflow/report/config.html
mccoy/workflow/report/formatted-bibliography.html
mccoy/workflow/report/mltree.html
mccoy/workflow/report/qc.html
mccoy/workflow/report/report-template.html
mccoy/workflow/rules/align.smk
mccoy/workflow/rules/beast.smk
mccoy/workflow/rules/combine.smk
mccoy/workflow/rules/dynamicbeast.smk
mccoy/workflow/rules/phytest.smk
mccoy/workflow/rules/report.smk
mccoy/workflow/rules/tree.smk
mccoy/workflow/scripts/alignment_html.py
mccoy/workflow/scripts/arviz_output.py
mccoy/workflow/scripts/pairwise_identity_histogram.py
mccoy/workflow/scripts/plot_traces.py
mccoy/workflow/scripts/render_tree.py
mccoy/workflow/scripts/report.py
mccoy/workflow/scripts/tree_converter.py
mccoy-0.1.2.dist-info/entry_points.txt
mccoy-0.1.2.dist-info/LICENSE
mccoy-0.1.2.dist-info/WHEEL
mccoy-0.1.2.dist-info/METADATA
mccoy-0.1.2.dist-info/RECORD
