Metadata-Version: 2.1
Name: mccoy
Version: 0.1.2
Summary: 
Author: Wytamma Wirth
Author-email: wytamma.wirth@me.com
Requires-Python: >=3.7,<4.0
Classifier: Programming Language :: Python :: 3
Classifier: Programming Language :: Python :: 3.7
Classifier: Programming Language :: Python :: 3.8
Classifier: Programming Language :: Python :: 3.9
Classifier: Programming Language :: Python :: 3.10
Requires-Dist: Jinja2 (>=3.1.2,<4.0.0)
Requires-Dist: setuptools (>=63.4.1,<64.0.0)
Requires-Dist: snakemake (>=7.5.0,<8.0.0)
Requires-Dist: tqdm (>=4.64.0,<5.0.0)
Requires-Dist: typer (>=0.4.1,<0.5.0)
